fluentc_langchain_tool/__init__.py
fluentc_langchain_tool/client.py
fluentc_langchain_tool/schemas.py
fluentc_langchain_tool/tool.py
fluentc_langchain_tool-0.2.0.dist-info/METADATA
fluentc_langchain_tool-0.2.0.dist-info/WHEEL
fluentc_langchain_tool-0.2.0.dist-info/top_level.txt
fluentc_langchain_tool-0.2.0.dist-info/RECORD
