Metadata-Version: 2.4
Name: fluentc-langchain-tool
Version: 0.2.0
Summary: Modern LangChain-compatible toolkit for FluentC AI Agent Translation API with real-time and batch translation support
Author: FluentC AI Team
Author-email: FluentC AI <support@fluentc.ai>
License: MIT
Project-URL: Homepage, https://www.fluentc.io
Project-URL: Documentation, https://dashboard.fluentc.io/ai_agent/docs
Project-URL: Repository, https://github.com/fluentc-ai/langchain-plugin
Project-URL: Issues, https://github.com/fluentc-ai/langchain-plugin/issues
Keywords: LangChain,Translation,FluentC,batch,realtime,AI,agent,multilingual,plugin
Classifier: Development Status :: 4 - Beta
Classifier: Intended Audience :: Developers
Classifier: Topic :: Software Development :: Libraries :: Python Modules
Classifier: Topic :: Text Processing :: Linguistic
Classifier: Topic :: Scientific/Engineering :: Artificial Intelligence
Classifier: Programming Language :: Python :: 3
Classifier: Programming Language :: Python :: 3.8
Classifier: Programming Language :: Python :: 3.9
Classifier: Programming Language :: Python :: 3.10
Classifier: Programming Language :: Python :: 3.11
Classifier: Programming Language :: Python :: 3.12
Classifier: License :: OSI Approved :: MIT License
Classifier: Operating System :: OS Independent
Requires-Python: >=3.8
Requires-Dist: requests>=2.28.0
Requires-Dist: pydantic>=1.10.0
Requires-Dist: langchain>=0.1.0
Requires-Dist: typing-extensions>=4.0.0; python_version < "3.10"
Provides-Extra: dev
Requires-Dist: pytest>=7.0.0; extra == "dev"
Requires-Dist: pytest-asyncio>=0.21.0; extra == "dev"
Requires-Dist: black>=23.0.0; extra == "dev"
Requires-Dist: mypy>=1.0.0; extra == "dev"
Requires-Dist: ruff>=0.1.0; extra == "dev"
